<?xml version="1.0" encoding="utf-8" ?>
<dwsync>
<file name="logo.png" server="jjy6190.dothome.co.kr" local="132992227982752474" remote="132992254800000000" Dst="0" />
<file name="center_1.png" server="jjy6190.dothome.co.kr" local="132992343015958528" remote="132992254800000000" Dst="0" />
<file name="center_menu.png" server="jjy6190.dothome.co.kr" local="132992482660535482" remote="132992254800000000" Dst="0" />
<file name="food_1.png" server="jjy6190.dothome.co.kr" local="132992444785992936" remote="132992254800000000" Dst="0" />
<file name="food_4.png" server="jjy6190.dothome.co.kr" local="132992445617212928" remote="132992254800000000" Dst="0" />
<file name="food_2.png" server="jjy6190.dothome.co.kr" local="132992445105812939" remote="132992254800000000" Dst="0" />
<file name="food_3.png" server="jjy6190.dothome.co.kr" local="132992445371212926" remote="132992254800000000" Dst="0" />
<file name="center_menu_bottom.png" server="jjy6190.dothome.co.kr" local="132992513054563356" remote="132992254800000000" Dst="0" />
</dwsync>